thoaded.py
thoaded-0.1.0.dist-info/LICENSE
thoaded-0.1.0.dist-info/METADATA
thoaded-0.1.0.dist-info/WHEEL
thoaded-0.1.0.dist-info/top_level.txt
thoaded-0.1.0.dist-info/RECORD
