Metadata-Version: 2.1
Name: thoaded
Version: 0.1.0
Summary: Library for simple and fast design pattern that extends model, view and controller for asynchronous events in supported modern programming languages.
Home-page: https://thoaded.walberbeltrame.com/
Author: Walber Antonio Ramos Beltrame
Author-email: walber.beltrame@gmail.com
License: MIT
Platform: UNKNOWN
Classifier: Programming Language :: Python :: 3
Classifier: License :: OSI Approved :: MIT License
Classifier: Operating System :: OS Independent
Requires-Python: >=3.6
